tno/quantum/ml/datasets/__init__.py
tno/quantum/ml/datasets/_anomalous_spiky_time_series.py
tno/quantum/ml/datasets/_bars_and_stripes.py
tno/quantum/ml/datasets/_blobs_clustering.py
tno/quantum/ml/datasets/_circles.py
tno/quantum/ml/datasets/_iris.py
tno/quantum/ml/datasets/_linearly_separable.py
tno/quantum/ml/datasets/_moons.py
tno/quantum/ml/datasets/_utils.py
tno/quantum/ml/datasets/_wine.py
tno/quantum/ml/datasets/py.typed
tno/quantum/ml/datasets/test/test_datasets.py
tno_quantum_ml_datasets-2.1.1.dist-info/licenses/LICENSE
tno_quantum_ml_datasets-2.1.1.dist-info/METADATA
tno_quantum_ml_datasets-2.1.1.dist-info/WHEEL
tno_quantum_ml_datasets-2.1.1.dist-info/top_level.txt
tno_quantum_ml_datasets-2.1.1.dist-info/RECORD
